mprequest/__init__.py
mprequest/request.py
mprequest/util.py
mprequest-0.2.1.dist-info/DESCRIPTION.rst
mprequest-0.2.1.dist-info/METADATA
mprequest-0.2.1.dist-info/RECORD
mprequest-0.2.1.dist-info/WHEEL
mprequest-0.2.1.dist-info/metadata.json
mprequest-0.2.1.dist-info/top_level.txt
