Metadata-Version: 2.0
Name: mprequest
Version: 0.2.1
Summary: MP Requesting Library
Home-page: UNKNOWN
Author: John Hopper
Author-email: john.hopper@jpserver.net
License: UNKNOWN
Platform: UNKNOWN
Requires-Dist: requests (>=2.12.4)
